cdk_code_server/__init__.py
cdk_code_server/py.typed
cdk_code_server/_jsii/__init__.py
cdk_code_server/_jsii/cdk-code-server@1.0.7.jsii.tgz
cdk_code_server-1.0.7.dist-info/LICENSE
cdk_code_server-1.0.7.dist-info/METADATA
cdk_code_server-1.0.7.dist-info/WHEEL
cdk_code_server-1.0.7.dist-info/top_level.txt
cdk_code_server-1.0.7.dist-info/RECORD
